{"currentSeason": {"data": {"type": "playerSeason", "attributes": {"gameModeStats": {"duo": {"assists": 0, "bestRankPoint": 0, "boosts": 0, "dBNOs": 0, "dailyKills": 0, "dailyWins": 0, "damageDealt": 0, "days": 0, "headshotKills": 0, "heals": 0, "killPoints": 0, "kills": 0, "longestKill": 0, "longestTimeSurvived": 0, "losses": 0, "maxKillStreaks": 0, "mostSurvivalTime": 0, "rankPoints": 0, "rankPointsTitle": "", "revives": 0, "rideDistance": 0, "roadKills": 0, "roundMostKills": 0, "roundsPlayed": 0, "suicides": 0, "swimDistance": 0, "teamKills": 0, "timeSurvived": 0, "top10s": 0, "vehicleDestroys": 0, "walkDistance": 0, "weaponsAcquired": 0, "weeklyKills": 0, "weeklyWins": 0, "winPoints": 0, "wins": 0}, "duo-fpp": {"assists": 0, "bestRankPoint": 0, "boosts": 0, "dBNOs": 0, "dailyKills": 0, "dailyWins": 0, "damageDealt": 0, "days": 0, "headshotKills": 0, "heals": 0, "killPoints": 0, "kills": 0, "longestKill": 0, "longestTimeSurvived": 0, "losses": 0, "maxKillStreaks": 0, "mostSurvivalTime": 0, "rankPoints": 0, "rankPointsTitle": "", "revives": 0, "rideDistance": 0, "roadKills": 0, "roundMostKills": 0, "roundsPlayed": 0, "suicides": 0, "swimDistance": 0, "teamKills": 0, "timeSurvived": 0, "top10s": 0, "vehicleDestroys": 0, "walkDistance": 0, "weaponsAcquired": 0, "weeklyKills": 0, "weeklyWins": 0, "winPoints": 0, "wins": 0}, "solo": {"assists": 0, "bestRankPoint": 8.437519, "boosts": 2, "dBNOs": 0, "dailyKills": 1, "dailyWins": 0, "damageDealt": 122.86015, "days": 1, "headshotKills": 0, "heals": 1, "killPoints": 0, "kills": 1, "longestKill": 2.7465687, "longestTimeSurvived": 485.274, "losses": 1, "maxKillStreaks": 1, "mostSurvivalTime": 485.274, "rankPoints": 8.437519, "rankPointsTitle": "1-5", "revives": 0, "rideDistance": 0, "roadKills": 0, "roundMostKills": 1, "roundsPlayed": 1, "suicides": 0, "swimDistance": 0, "teamKills": 0, "timeSurvived": 485.274, "top10s": 0, "vehicleDestroys": 0, "walkDistance": 707.52313, "weaponsAcquired": 4, "weeklyKills": 1, "weeklyWins": 0, "winPoints": 0, "wins": 0}, "solo-fpp": {"assists": 0, "bestRankPoint": 0, "boosts": 0, "dBNOs": 0, "dailyKills": 0, "dailyWins": 0, "damageDealt": 0, "days": 0, "headshotKills": 0, "heals": 0, "killPoints": 0, "kills": 0, "longestKill": 0, "longestTimeSurvived": 0, "losses": 0, "maxKillStreaks": 0, "mostSurvivalTime": 0, "rankPoints": 0, "rankPointsTitle": "", "revives": 0, "rideDistance": 0, "roadKills": 0, "roundMostKills": 0, "roundsPlayed": 0, "suicides": 0, "swimDistance": 0, "teamKills": 0, "timeSurvived": 0, "top10s": 0, "vehicleDestroys": 0, "walkDistance": 0, "weaponsAcquired": 0, "weeklyKills": 0, "weeklyWins": 0, "winPoints": 0, "wins": 0}, "squad": {"assists": 28, "bestRankPoint": 1137.6377, "boosts": 163, "dBNOs": 177, "dailyKills": 150, "dailyWins": 5, "damageDealt": 25750.7, "days": 3, "headshotKills": 55, "heals": 103, "killPoints": 0, "kills": 211, "longestKill": 336.09235, "longestTimeSurvived": 1897.922, "losses": 47, "maxKillStreaks": 4, "mostSurvivalTime": 1897.922, "rankPoints": 1137.6377, "rankPointsTitle": "2-5", "revives": 22, "rideDistance": 19917.787, "roadKills": 0, "roundMostKills": 14, "roundsPlayed": 55, "suicides": 1, "swimDistance": 137.15118, "teamKills": 1, "timeSurvived": 41614.207, "top10s": 22, "vehicleDestroys": 0, "walkDistance": 85873.11, "weaponsAcquired": 180, "weeklyKills": 207, "weeklyWins": 8, "winPoints": 0, "wins": 8}, "squad-fpp": {"assists": 0, "bestRankPoint": 0, "boosts": 0, "dBNOs": 0, "dailyKills": 0, "dailyWins": 0, "damageDealt": 0, "days": 0, "headshotKills": 0, "heals": 0, "killPoints": 0, "kills": 0, "longestKill": 0, "longestTimeSurvived": 0, "losses": 0, "maxKillStreaks": 0, "mostSurvivalTime": 0, "rankPoints": 0, "rankPointsTitle": "", "revives": 0, "rideDistance": 0, "roadKills": 0, "roundMostKills": 0, "roundsPlayed": 0, "suicides": 0, "swimDistance": 0, "teamKills": 0, "timeSurvived": 0, "top10s": 0, "vehicleDestroys": 0, "walkDistance": 0, "weaponsAcquired": 0, "weeklyKills": 0, "weeklyWins": 0, "winPoints": 0, "wins": 0}}}, "relationships": {"matchesSquad": {"data": [{"type": "match", "id": "8825f19f-4001-4d4c-ae43-16715d7bc85b"}, {"type": "match", "id": "5b5430a8-c969-41e3-b257-6f2f51c227e1"}, {"type": "match", "id": "f2a0172a-c76f-4814-8823-f85c7499a203"}, {"type": "match", "id": "8511d020-feff-4c7e-a917-97d4ced870a9"}, {"type": "match", "id": "f388d31e-19d7-4a59-a06c-35a0c27e23b9"}, {"type": "match", "id": "9a651390-b8e2-4549-9462-72aaabe3ec7b"}, {"type": "match", "id": "8f05161f-5868-4dd7-9dcc-9a35d8f5cfe7"}, {"type": "match", "id": "8a5e1e72-e0c9-4f4d-9ff3-df0f1ea05419"}, {"type": "match", "id": "83365d8f-fcb1-4bfa-beea-204e20bba991"}, {"type": "match", "id": "9724c46d-b559-4cec-b469-c9c8bb355438"}, {"type": "match", "id": "87a7a861-e059-4175-a9b7-7b5667946119"}, {"type": "match", "id": "02fe3f6f-13c8-4fa1-b8e7-d9b824aeedce"}, {"type": "match", "id": "3054c6e1-6eff-487f-8be4-7b8cff53dde2"}, {"type": "match", "id": "b6f2498a-3ea8-45a4-a247-27971e806e5b"}, {"type": "match", "id": "d847fca3-e17d-426c-b383-2f6cf755d6ed"}, {"type": "match", "id": "1d66e1ed-73cd-4d3c-bdd3-04f56e76095a"}, {"type": "match", "id": "bff76acc-a508-4389-bf0a-d962f17e5448"}, {"type": "match", "id": "ab3fabba-a95b-40d7-8c2a-74702f2eee5c"}, {"type": "match", "id": "9aa6ecc2-e50d-44b8-925e-53c3e0384e6b"}, {"type": "match", "id": "5a5ec422-3849-4fed-9234-4c26ee92af42"}, {"type": "match", "id": "22b9f6b4-0bed-49a6-9861-c8b5eb6d7845"}, {"type": "match", "id": "a62c79cc-fdc4-496a-9bd8-b3cfb344f89b"}, {"type": "match", "id": "6ed1a56a-c55e-48f4-ae99-bdb178f3dd64"}, {"type": "match", "id": "03853a22-1ae0-4e73-8dbe-25840dfccc79"}, {"type": "match", "id": "129c7e79-3130-4e62-a8f4-6876e05510e1"}, {"type": "match", "id": "4103a316-fceb-453b-808a-871b937611a2"}, {"type": "match", "id": "7c88150c-7afd-4477-abbe-77a66f534b09"}, {"type": "match", "id": "c450fd0f-779d-467d-8977-c7e142bc5c2b"}, {"type": "match", "id": "0c54e59c-092a-46f7-8f33-ed85f0cafc6a"}, {"type": "match", "id": "666cc668-4b93-42cc-914b-195d044a798e"}, {"type": "match", "id": "5d02f8d9-951b-426a-9d5f-2bc2f2a67f3b"}, {"type": "match", "id": "5231bdca-5a8f-4a1a-9353-9aa119956ac6"}]}, "matchesSquadFPP": {"data": []}, "season": {"data": {"type": "season", "id": "division.bro.official.pc-2018-02"}}, "player": {"data": {"type": "player", "id": "account.1be2d844cc7d4be8b09877546eb02f1a"}}, "matchesSolo": {"data": [{"type": "match", "id": "520662eb-9381-4f4d-8ccf-ac1964ecbcf8"}]}, "matchesSoloFPP": {"data": []}, "matchesDuo": {"data": []}, "matchesDuoFPP": {"data": []}}}, "links": {"self": "https://api.pubg.com/shards/kakao/players/account.1be2d844cc7d4be8b09877546eb02f1a/seasons/division.bro.official.pc-2018-02"}, "meta": {}}, "previousSeason": {"data": {"type": "playerSeason", "attributes": {"gameModeStats": {"duo": {"assists": 0, "bestRankPoint": 0, "boosts": 0, "dBNOs": 0, "dailyKills": 0, "dailyWins": 0, "damageDealt": 0, "days": 0, "headshotKills": 0, "heals": 0, "killPoints": 0, "kills": 0, "longestKill": 0, "longestTimeSurvived": 0, "losses": 0, "maxKillStreaks": 0, "mostSurvivalTime": 0, "rankPoints": 0, "rankPointsTitle": "", "revives": 0, "rideDistance": 0, "roadKills": 0, "roundMostKills": 0, "roundsPlayed": 0, "suicides": 0, "swimDistance": 0, "teamKills": 0, "timeSurvived": 0, "top10s": 0, "vehicleDestroys": 0, "walkDistance": 0, "weaponsAcquired": 0, "weeklyKills": 0, "weeklyWins": 0, "winPoints": 0, "wins": 0}, "duo-fpp": {"assists": 0, "bestRankPoint": 0, "boosts": 0, "dBNOs": 0, "dailyKills": 0, "dailyWins": 0, "damageDealt": 0, "days": 0, "headshotKills": 0, "heals": 0, "killPoints": 0, "kills": 0, "longestKill": 0, "longestTimeSurvived": 0, "losses": 0, "maxKillStreaks": 0, "mostSurvivalTime": 0, "rankPoints": 0, "rankPointsTitle": "", "revives": 0, "rideDistance": 0, "roadKills": 0, "roundMostKills": 0, "roundsPlayed": 0, "suicides": 0, "swimDistance": 0, "teamKills": 0, "timeSurvived": 0, "top10s": 0, "vehicleDestroys": 0, "walkDistance": 0, "weaponsAcquired": 0, "weeklyKills": 0, "weeklyWins": 0, "winPoints": 0, "wins": 0}, "solo": {"assists": 0, "bestRankPoint": 8.437519, "boosts": 2, "dBNOs": 0, "dailyKills": 1, "dailyWins": 0, "damageDealt": 122.86015, "days": 1, "headshotKills": 0, "heals": 1, "killPoints": 0, "kills": 1, "longestKill": 2.7465687, "longestTimeSurvived": 485.274, "losses": 1, "maxKillStreaks": 1, "mostSurvivalTime": 485.274, "rankPoints": 8.437519, "rankPointsTitle": "1-5", "revives": 0, "rideDistance": 0, "roadKills": 0, "roundMostKills": 1, "roundsPlayed": 1, "suicides": 0, "swimDistance": 0, "teamKills": 0, "timeSurvived": 485.274, "top10s": 0, "vehicleDestroys": 0, "walkDistance": 707.52313, "weaponsAcquired": 4, "weeklyKills": 1, "weeklyWins": 0, "winPoints": 0, "wins": 0}, "solo-fpp": {"assists": 0, "bestRankPoint": 0, "boosts": 0, "dBNOs": 0, "dailyKills": 0, "dailyWins": 0, "damageDealt": 0, "days": 0, "headshotKills": 0, "heals": 0, "killPoints": 0, "kills": 0, "longestKill": 0, "longestTimeSurvived": 0, "losses": 0, "maxKillStreaks": 0, "mostSurvivalTime": 0, "rankPoints": 0, "rankPointsTitle": "", "revives": 0, "rideDistance": 0, "roadKills": 0, "roundMostKills": 0, "roundsPlayed": 0, "suicides": 0, "swimDistance": 0, "teamKills": 0, "timeSurvived": 0, "top10s": 0, "vehicleDestroys": 0, "walkDistance": 0, "weaponsAcquired": 0, "weeklyKills": 0, "weeklyWins": 0, "winPoints": 0, "wins": 0}, "squad": {"assists": 28, "bestRankPoint": 1137.6377, "boosts": 163, "dBNOs": 177, "dailyKills": 150, "dailyWins": 5, "damageDealt": 25750.7, "days": 3, "headshotKills": 55, "heals": 103, "killPoints": 0, "kills": 211, "longestKill": 336.09235, "longestTimeSurvived": 1897.922, "losses": 47, "maxKillStreaks": 4, "mostSurvivalTime": 1897.922, "rankPoints": 1137.6377, "rankPointsTitle": "2-5", "revives": 22, "rideDistance": 19917.787, "roadKills": 0, "roundMostKills": 14, "roundsPlayed": 55, "suicides": 1, "swimDistance": 137.15118, "teamKills": 1, "timeSurvived": 41614.207, "top10s": 22, "vehicleDestroys": 0, "walkDistance": 85873.11, "weaponsAcquired": 180, "weeklyKills": 207, "weeklyWins": 8, "winPoints": 0, "wins": 8}, "squad-fpp": {"assists": 0, "bestRankPoint": 0, "boosts": 0, "dBNOs": 0, "dailyKills": 0, "dailyWins": 0, "damageDealt": 0, "days": 0, "headshotKills": 0, "heals": 0, "killPoints": 0, "kills": 0, "longestKill": 0, "longestTimeSurvived": 0, "losses": 0, "maxKillStreaks": 0, "mostSurvivalTime": 0, "rankPoints": 0, "rankPointsTitle": "", "revives": 0, "rideDistance": 0, "roadKills": 0, "roundMostKills": 0, "roundsPlayed": 0, "suicides": 0, "swimDistance": 0, "teamKills": 0, "timeSurvived": 0, "top10s": 0, "vehicleDestroys": 0, "walkDistance": 0, "weaponsAcquired": 0, "weeklyKills": 0, "weeklyWins": 0, "winPoints": 0, "wins": 0}}}, "relationships": {"season": {"data": {"type": "season", "id": "division.bro.official.pc-2018-02"}}, "player": {"data": {"type": "player", "id": "account.1be2d844cc7d4be8b09877546eb02f1a"}}, "matchesSolo": {"data": [{"type": "match", "id": "520662eb-9381-4f4d-8ccf-ac1964ecbcf8"}]}, "matchesSoloFPP": {"data": []}, "matchesDuo": {"data": []}, "matchesDuoFPP": {"data": []}, "matchesSquad": {"data": [{"type": "match", "id": "8825f19f-4001-4d4c-ae43-16715d7bc85b"}, {"type": "match", "id": "5b5430a8-c969-41e3-b257-6f2f51c227e1"}, {"type": "match", "id": "f2a0172a-c76f-4814-8823-f85c7499a203"}, {"type": "match", "id": "8511d020-feff-4c7e-a917-97d4ced870a9"}, {"type": "match", "id": "f388d31e-19d7-4a59-a06c-35a0c27e23b9"}, {"type": "match", "id": "9a651390-b8e2-4549-9462-72aaabe3ec7b"}, {"type": "match", "id": "8f05161f-5868-4dd7-9dcc-9a35d8f5cfe7"}, {"type": "match", "id": "8a5e1e72-e0c9-4f4d-9ff3-df0f1ea05419"}, {"type": "match", "id": "83365d8f-fcb1-4bfa-beea-204e20bba991"}, {"type": "match", "id": "9724c46d-b559-4cec-b469-c9c8bb355438"}, {"type": "match", "id": "87a7a861-e059-4175-a9b7-7b5667946119"}, {"type": "match", "id": "02fe3f6f-13c8-4fa1-b8e7-d9b824aeedce"}, {"type": "match", "id": "3054c6e1-6eff-487f-8be4-7b8cff53dde2"}, {"type": "match", "id": "b6f2498a-3ea8-45a4-a247-27971e806e5b"}, {"type": "match", "id": "d847fca3-e17d-426c-b383-2f6cf755d6ed"}, {"type": "match", "id": "1d66e1ed-73cd-4d3c-bdd3-04f56e76095a"}, {"type": "match", "id": "bff76acc-a508-4389-bf0a-d962f17e5448"}, {"type": "match", "id": "ab3fabba-a95b-40d7-8c2a-74702f2eee5c"}, {"type": "match", "id": "9aa6ecc2-e50d-44b8-925e-53c3e0384e6b"}, {"type": "match", "id": "5a5ec422-3849-4fed-9234-4c26ee92af42"}, {"type": "match", "id": "22b9f6b4-0bed-49a6-9861-c8b5eb6d7845"}, {"type": "match", "id": "a62c79cc-fdc4-496a-9bd8-b3cfb344f89b"}, {"type": "match", "id": "6ed1a56a-c55e-48f4-ae99-bdb178f3dd64"}, {"type": "match", "id": "03853a22-1ae0-4e73-8dbe-25840dfccc79"}, {"type": "match", "id": "129c7e79-3130-4e62-a8f4-6876e05510e1"}, {"type": "match", "id": "4103a316-fceb-453b-808a-871b937611a2"}, {"type": "match", "id": "7c88150c-7afd-4477-abbe-77a66f534b09"}, {"type": "match", "id": "c450fd0f-779d-467d-8977-c7e142bc5c2b"}, {"type": "match", "id": "0c54e59c-092a-46f7-8f33-ed85f0cafc6a"}, {"type": "match", "id": "666cc668-4b93-42cc-914b-195d044a798e"}, {"type": "match", "id": "5d02f8d9-951b-426a-9d5f-2bc2f2a67f3b"}, {"type": "match", "id": "5231bdca-5a8f-4a1a-9353-9aa119956ac6"}]}, "matchesSquadFPP": {"data": []}}}, "links": {"self": "https://api.pubg.com/shards/kakao/players/account.1be2d844cc7d4be8b09877546eb02f1a/seasons/division.bro.official.pc-2018-02"}, "meta": {}}}