{"currentSeason": {"data": {"type": "playerSeason", "attributes": {"gameModeStats": {"duo": {"assists": 1, "bestRankPoint": 130.5778, "boosts": 8, "dBNOs": 10, "dailyKills": 24, "dailyWins": 2, "damageDealt": 2744.6313, "days": 1, "headshotKills": 11, "heals": 2, "killPoints": 0, "kills": 24, "longestKill": 258.54712, "longestTimeSurvived": 1823.137, "losses": 0, "maxKillStreaks": 3, "mostSurvivalTime": 1823.137, "rankPoints": 130.5778, "rankPointsTitle": "1-5", "revives": 0, "rideDistance": 3700.2585, "roadKills": 0, "roundMostKills": 14, "roundsPlayed": 2, "suicides": 0, "swimDistance": 343.45956, "teamKills": 0, "timeSurvived": 3118.76, "top10s": 2, "vehicleDestroys": 0, "walkDistance": 4976.2036, "weaponsAcquired": 12, "weeklyKills": 24, "weeklyWins": 2, "winPoints": 0, "wins": 2}, "duo-fpp": {"assists": 0, "bestRankPoint": 0, "boosts": 0, "dBNOs": 0, "dailyKills": 0, "dailyWins": 0, "damageDealt": 0, "days": 0, "headshotKills": 0, "heals": 0, "killPoints": 0, "kills": 0, "longestKill": 0, "longestTimeSurvived": 0, "losses": 0, "maxKillStreaks": 0, "mostSurvivalTime": 0, "rankPoints": 0, "rankPointsTitle": "", "revives": 0, "rideDistance": 0, "roadKills": 0, "roundMostKills": 0, "roundsPlayed": 0, "suicides": 0, "swimDistance": 0, "teamKills": 0, "timeSurvived": 0, "top10s": 0, "vehicleDestroys": 0, "walkDistance": 0, "weaponsAcquired": 0, "weeklyKills": 0, "weeklyWins": 0, "winPoints": 0, "wins": 0}, "solo": {"assists": 0, "bestRankPoint": 0, "boosts": 0, "dBNOs": 0, "dailyKills": 0, "dailyWins": 0, "damageDealt": 0, "days": 0, "headshotKills": 0, "heals": 0, "killPoints": 0, "kills": 0, "longestKill": 0, "longestTimeSurvived": 0, "losses": 0, "maxKillStreaks": 0, "mostSurvivalTime": 0, "rankPoints": 0, "rankPointsTitle": "", "revives": 0, "rideDistance": 0, "roadKills": 0, "roundMostKills": 0, "roundsPlayed": 0, "suicides": 0, "swimDistance": 0, "teamKills": 0, "timeSurvived": 0, "top10s": 0, "vehicleDestroys": 0, "walkDistance": 0, "weaponsAcquired": 0, "weeklyKills": 0, "weeklyWins": 0, "winPoints": 0, "wins": 0}, "solo-fpp": {"assists": 0, "bestRankPoint": 0, "boosts": 0, "dBNOs": 0, "dailyKills": 0, "dailyWins": 0, "damageDealt": 0, "days": 0, "headshotKills": 0, "heals": 0, "killPoints": 0, "kills": 0, "longestKill": 0, "longestTimeSurvived": 0, "losses": 0, "maxKillStreaks": 0, "mostSurvivalTime": 0, "rankPoints": 0, "rankPointsTitle": "", "revives": 0, "rideDistance": 0, "roadKills": 0, "roundMostKills": 0, "roundsPlayed": 0, "suicides": 0, "swimDistance": 0, "teamKills": 0, "timeSurvived": 0, "top10s": 0, "vehicleDestroys": 0, "walkDistance": 0, "weaponsAcquired": 0, "weeklyKills": 0, "weeklyWins": 0, "winPoints": 0, "wins": 0}, "squad": {"assists": 16, "bestRankPoint": 863.6436, "boosts": 69, "dBNOs": 125, "dailyKills": 126, "dailyWins": 11, "damageDealt": 16641.71, "days": 1, "headshotKills": 48, "heals": 53, "killPoints": 0, "kills": 126, "longestKill": 491.0499, "longestTimeSurvived": 1962.11, "losses": 20, "maxKillStreaks": 4, "mostSurvivalTime": 1962.11, "rankPoints": 863.6436, "rankPointsTitle": "1-1", "revives": 7, "rideDistance": 43385.027, "roadKills": 0, "roundMostKills": 13, "roundsPlayed": 26, "suicides": 0, "swimDistance": 200.4447, "teamKills": 1, "timeSurvived": 30103.816, "top10s": 16, "vehicleDestroys": 2, "walkDistance": 54610.52, "weaponsAcquired": 113, "weeklyKills": 126, "weeklyWins": 11, "winPoints": 0, "wins": 11}, "squad-fpp": {"assists": 0, "bestRankPoint": 0, "boosts": 0, "dBNOs": 0, "dailyKills": 0, "dailyWins": 0, "damageDealt": 0, "days": 0, "headshotKills": 0, "heals": 0, "killPoints": 0, "kills": 0, "longestKill": 0, "longestTimeSurvived": 0, "losses": 0, "maxKillStreaks": 0, "mostSurvivalTime": 0, "rankPoints": 0, "rankPointsTitle": "", "revives": 0, "rideDistance": 0, "roadKills": 0, "roundMostKills": 0, "roundsPlayed": 0, "suicides": 0, "swimDistance": 0, "teamKills": 0, "timeSurvived": 0, "top10s": 0, "vehicleDestroys": 0, "walkDistance": 0, "weaponsAcquired": 0, "weeklyKills": 0, "weeklyWins": 0, "winPoints": 0, "wins": 0}}}, "relationships": {"matchesDuoFPP": {"data": []}, "matchesSquad": {"data": [{"type": "match", "id": "7bf70441-ac3f-4902-b0e0-03641186d366"}, {"type": "match", "id": "b564a5c4-411c-4f56-a0d7-011306088cc5"}, {"type": "match", "id": "bb283313-b040-4238-8acd-e4bd44fb8d63"}, {"type": "match", "id": "a5be057a-6ca6-4074-af8b-44528ad01013"}, {"type": "match", "id": "6b7b370e-1dbc-44e6-86f1-cfa4009a9239"}, {"type": "match", "id": "1c85f5ef-7500-467e-95e1-8f6b68854d15"}, {"type": "match", "id": "bc44dc85-90f6-474d-8613-a020c7236ec0"}, {"type": "match", "id": "79e89185-00a7-461c-8841-39bd66544106"}, {"type": "match", "id": "fe3360fe-8c4f-4f22-9b2e-a4d802f0586a"}, {"type": "match", "id": "18d2c47c-8f2a-470d-b154-9b357e28dbd9"}, {"type": "match", "id": "79102c85-0df5-4546-af59-10db439b4cbb"}, {"type": "match", "id": "e7253e8d-3f5c-4070-b71c-c9b14f50776c"}, {"type": "match", "id": "cc48d27c-4283-4cd5-ab85-7eec6d0faf8c"}, {"type": "match", "id": "f94c4a5c-9715-4507-ae94-f25785162228"}, {"type": "match", "id": "c8588717-f3d1-48ae-adcb-b8e17dba36bf"}, {"type": "match", "id": "03a35b2b-c5df-4c14-9199-74be77229398"}, {"type": "match", "id": "65612d38-e31f-40ff-9437-8db21d23ed0a"}, {"type": "match", "id": "52459358-c40d-4919-bace-8c6c060e6cd7"}, {"type": "match", "id": "2d25428d-6484-4ed7-845d-b058bcb64d20"}, {"type": "match", "id": "f92abb27-bce6-4c13-a504-42e544a2dcf4"}, {"type": "match", "id": "8e334923-1102-4e20-885d-7aa029c7f5fe"}, {"type": "match", "id": "f9fdd494-36ba-42c4-8dda-c6c3df24d468"}, {"type": "match", "id": "555189c0-8628-4701-9974-8729b64437fe"}, {"type": "match", "id": "19431068-2364-4b55-a0bc-263d1fafd75d"}, {"type": "match", "id": "df9d0b18-a172-411d-bf60-aa53b0ecd986"}, {"type": "match", "id": "a2a51ce6-f549-44d6-88b2-67ab33bd9da7"}]}, "matchesSquadFPP": {"data": []}, "season": {"data": {"type": "season", "id": "division.bro.official.pc-2018-02"}}, "player": {"data": {"type": "player", "id": "account.7b3b74404eb74793b71049068bb1d851"}}, "matchesSolo": {"data": []}, "matchesSoloFPP": {"data": []}, "matchesDuo": {"data": [{"type": "match", "id": "f61d0e73-6bcf-4393-809d-0606a7176b3e"}, {"type": "match", "id": "2084c347-744c-4b7a-ab19-e31e444d54d7"}]}}}, "links": {"self": "https://api.pubg.com/shards/kakao/players/account.7b3b74404eb74793b71049068bb1d851/seasons/division.bro.official.pc-2018-02"}, "meta": {}}, "previousSeason": {"data": {"type": "playerSeason", "attributes": {"gameModeStats": {"duo": {"assists": 1, "bestRankPoint": 130.5778, "boosts": 8, "dBNOs": 10, "dailyKills": 24, "dailyWins": 2, "damageDealt": 2744.6313, "days": 1, "headshotKills": 11, "heals": 2, "killPoints": 0, "kills": 24, "longestKill": 258.54712, "longestTimeSurvived": 1823.137, "losses": 0, "maxKillStreaks": 3, "mostSurvivalTime": 1823.137, "rankPoints": 130.5778, "rankPointsTitle": "1-5", "revives": 0, "rideDistance": 3700.2585, "roadKills": 0, "roundMostKills": 14, "roundsPlayed": 2, "suicides": 0, "swimDistance": 343.45956, "teamKills": 0, "timeSurvived": 3118.76, "top10s": 2, "vehicleDestroys": 0, "walkDistance": 4976.2036, "weaponsAcquired": 12, "weeklyKills": 24, "weeklyWins": 2, "winPoints": 0, "wins": 2}, "duo-fpp": {"assists": 0, "bestRankPoint": 0, "boosts": 0, "dBNOs": 0, "dailyKills": 0, "dailyWins": 0, "damageDealt": 0, "days": 0, "headshotKills": 0, "heals": 0, "killPoints": 0, "kills": 0, "longestKill": 0, "longestTimeSurvived": 0, "losses": 0, "maxKillStreaks": 0, "mostSurvivalTime": 0, "rankPoints": 0, "rankPointsTitle": "", "revives": 0, "rideDistance": 0, "roadKills": 0, "roundMostKills": 0, "roundsPlayed": 0, "suicides": 0, "swimDistance": 0, "teamKills": 0, "timeSurvived": 0, "top10s": 0, "vehicleDestroys": 0, "walkDistance": 0, "weaponsAcquired": 0, "weeklyKills": 0, "weeklyWins": 0, "winPoints": 0, "wins": 0}, "solo": {"assists": 0, "bestRankPoint": 0, "boosts": 0, "dBNOs": 0, "dailyKills": 0, "dailyWins": 0, "damageDealt": 0, "days": 0, "headshotKills": 0, "heals": 0, "killPoints": 0, "kills": 0, "longestKill": 0, "longestTimeSurvived": 0, "losses": 0, "maxKillStreaks": 0, "mostSurvivalTime": 0, "rankPoints": 0, "rankPointsTitle": "", "revives": 0, "rideDistance": 0, "roadKills": 0, "roundMostKills": 0, "roundsPlayed": 0, "suicides": 0, "swimDistance": 0, "teamKills": 0, "timeSurvived": 0, "top10s": 0, "vehicleDestroys": 0, "walkDistance": 0, "weaponsAcquired": 0, "weeklyKills": 0, "weeklyWins": 0, "winPoints": 0, "wins": 0}, "solo-fpp": {"assists": 0, "bestRankPoint": 0, "boosts": 0, "dBNOs": 0, "dailyKills": 0, "dailyWins": 0, "damageDealt": 0, "days": 0, "headshotKills": 0, "heals": 0, "killPoints": 0, "kills": 0, "longestKill": 0, "longestTimeSurvived": 0, "losses": 0, "maxKillStreaks": 0, "mostSurvivalTime": 0, "rankPoints": 0, "rankPointsTitle": "", "revives": 0, "rideDistance": 0, "roadKills": 0, "roundMostKills": 0, "roundsPlayed": 0, "suicides": 0, "swimDistance": 0, "teamKills": 0, "timeSurvived": 0, "top10s": 0, "vehicleDestroys": 0, "walkDistance": 0, "weaponsAcquired": 0, "weeklyKills": 0, "weeklyWins": 0, "winPoints": 0, "wins": 0}, "squad": {"assists": 16, "bestRankPoint": 863.6436, "boosts": 69, "dBNOs": 125, "dailyKills": 126, "dailyWins": 11, "damageDealt": 16641.71, "days": 1, "headshotKills": 48, "heals": 53, "killPoints": 0, "kills": 126, "longestKill": 491.0499, "longestTimeSurvived": 1962.11, "losses": 20, "maxKillStreaks": 4, "mostSurvivalTime": 1962.11, "rankPoints": 863.6436, "rankPointsTitle": "1-1", "revives": 7, "rideDistance": 43385.027, "roadKills": 0, "roundMostKills": 13, "roundsPlayed": 26, "suicides": 0, "swimDistance": 200.4447, "teamKills": 1, "timeSurvived": 30103.816, "top10s": 16, "vehicleDestroys": 2, "walkDistance": 54610.52, "weaponsAcquired": 113, "weeklyKills": 126, "weeklyWins": 11, "winPoints": 0, "wins": 11}, "squad-fpp": {"assists": 0, "bestRankPoint": 0, "boosts": 0, "dBNOs": 0, "dailyKills": 0, "dailyWins": 0, "damageDealt": 0, "days": 0, "headshotKills": 0, "heals": 0, "killPoints": 0, "kills": 0, "longestKill": 0, "longestTimeSurvived": 0, "losses": 0, "maxKillStreaks": 0, "mostSurvivalTime": 0, "rankPoints": 0, "rankPointsTitle": "", "revives": 0, "rideDistance": 0, "roadKills": 0, "roundMostKills": 0, "roundsPlayed": 0, "suicides": 0, "swimDistance": 0, "teamKills": 0, "timeSurvived": 0, "top10s": 0, "vehicleDestroys": 0, "walkDistance": 0, "weaponsAcquired": 0, "weeklyKills": 0, "weeklyWins": 0, "winPoints": 0, "wins": 0}}}, "relationships": {"matchesSoloFPP": {"data": []}, "matchesDuo": {"data": [{"type": "match", "id": "f61d0e73-6bcf-4393-809d-0606a7176b3e"}, {"type": "match", "id": "2084c347-744c-4b7a-ab19-e31e444d54d7"}]}, "matchesDuoFPP": {"data": []}, "matchesSquad": {"data": [{"type": "match", "id": "7bf70441-ac3f-4902-b0e0-03641186d366"}, {"type": "match", "id": "b564a5c4-411c-4f56-a0d7-011306088cc5"}, {"type": "match", "id": "bb283313-b040-4238-8acd-e4bd44fb8d63"}, {"type": "match", "id": "a5be057a-6ca6-4074-af8b-44528ad01013"}, {"type": "match", "id": "6b7b370e-1dbc-44e6-86f1-cfa4009a9239"}, {"type": "match", "id": "1c85f5ef-7500-467e-95e1-8f6b68854d15"}, {"type": "match", "id": "bc44dc85-90f6-474d-8613-a020c7236ec0"}, {"type": "match", "id": "79e89185-00a7-461c-8841-39bd66544106"}, {"type": "match", "id": "fe3360fe-8c4f-4f22-9b2e-a4d802f0586a"}, {"type": "match", "id": "18d2c47c-8f2a-470d-b154-9b357e28dbd9"}, {"type": "match", "id": "79102c85-0df5-4546-af59-10db439b4cbb"}, {"type": "match", "id": "e7253e8d-3f5c-4070-b71c-c9b14f50776c"}, {"type": "match", "id": "cc48d27c-4283-4cd5-ab85-7eec6d0faf8c"}, {"type": "match", "id": "f94c4a5c-9715-4507-ae94-f25785162228"}, {"type": "match", "id": "c8588717-f3d1-48ae-adcb-b8e17dba36bf"}, {"type": "match", "id": "03a35b2b-c5df-4c14-9199-74be77229398"}, {"type": "match", "id": "65612d38-e31f-40ff-9437-8db21d23ed0a"}, {"type": "match", "id": "52459358-c40d-4919-bace-8c6c060e6cd7"}, {"type": "match", "id": "2d25428d-6484-4ed7-845d-b058bcb64d20"}, {"type": "match", "id": "f92abb27-bce6-4c13-a504-42e544a2dcf4"}, {"type": "match", "id": "8e334923-1102-4e20-885d-7aa029c7f5fe"}, {"type": "match", "id": "f9fdd494-36ba-42c4-8dda-c6c3df24d468"}, {"type": "match", "id": "555189c0-8628-4701-9974-8729b64437fe"}, {"type": "match", "id": "19431068-2364-4b55-a0bc-263d1fafd75d"}, {"type": "match", "id": "df9d0b18-a172-411d-bf60-aa53b0ecd986"}, {"type": "match", "id": "a2a51ce6-f549-44d6-88b2-67ab33bd9da7"}]}, "matchesSquadFPP": {"data": []}, "season": {"data": {"type": "season", "id": "division.bro.official.pc-2018-02"}}, "player": {"data": {"type": "player", "id": "account.7b3b74404eb74793b71049068bb1d851"}}, "matchesSolo": {"data": []}}}, "links": {"self": "https://api.pubg.com/shards/kakao/players/account.7b3b74404eb74793b71049068bb1d851/seasons/division.bro.official.pc-2018-02"}, "meta": {}}}