{"currentSeason": {"data": {"type": "playerSeason", "attributes": {"gameModeStats": {"duo": {"assists": 0, "bestRankPoint": 45.698147, "boosts": 1, "dBNOs": 0, "dailyKills": 0, "dailyWins": 0, "damageDealt": 0, "days": 1, "headshotKills": 0, "heals": 2, "killPoints": 0, "kills": 0, "longestKill": 0, "longestTimeSurvived": 1481.129, "losses": 9, "maxKillStreaks": 0, "mostSurvivalTime": 1481.129, "rankPoints": 45.698147, "rankPointsTitle": "1-5", "revives": 1, "rideDistance": 4128.3467, "roadKills": 0, "roundMostKills": 0, "roundsPlayed": 9, "suicides": 0, "swimDistance": 0, "teamKills": 0, "timeSurvived": 3307.6948, "top10s": 1, "vehicleDestroys": 0, "walkDistance": 3749.1277, "weaponsAcquired": 36, "weeklyKills": 0, "weeklyWins": 0, "winPoints": 0, "wins": 0}, "duo-fpp": {"assists": 0, "bestRankPoint": 0, "boosts": 0, "dBNOs": 0, "dailyKills": 0, "dailyWins": 0, "damageDealt": 0, "days": 0, "headshotKills": 0, "heals": 0, "killPoints": 0, "kills": 0, "longestKill": 0, "longestTimeSurvived": 0, "losses": 0, "maxKillStreaks": 0, "mostSurvivalTime": 0, "rankPoints": 0, "rankPointsTitle": "", "revives": 0, "rideDistance": 0, "roadKills": 0, "roundMostKills": 0, "roundsPlayed": 0, "suicides": 0, "swimDistance": 0, "teamKills": 0, "timeSurvived": 0, "top10s": 0, "vehicleDestroys": 0, "walkDistance": 0, "weaponsAcquired": 0, "weeklyKills": 0, "weeklyWins": 0, "winPoints": 0, "wins": 0}, "solo": {"assists": 0, "bestRankPoint": 0, "boosts": 0, "dBNOs": 0, "dailyKills": 0, "dailyWins": 0, "damageDealt": 0, "days": 0, "headshotKills": 0, "heals": 0, "killPoints": 0, "kills": 0, "longestKill": 0, "longestTimeSurvived": 0, "losses": 0, "maxKillStreaks": 0, "mostSurvivalTime": 0, "rankPoints": 0, "rankPointsTitle": "", "revives": 0, "rideDistance": 0, "roadKills": 0, "roundMostKills": 0, "roundsPlayed": 0, "suicides": 0, "swimDistance": 0, "teamKills": 0, "timeSurvived": 0, "top10s": 0, "vehicleDestroys": 0, "walkDistance": 0, "weaponsAcquired": 0, "weeklyKills": 0, "weeklyWins": 0, "winPoints": 0, "wins": 0}, "solo-fpp": {"assists": 0, "bestRankPoint": 0, "boosts": 0, "dBNOs": 0, "dailyKills": 0, "dailyWins": 0, "damageDealt": 0, "days": 0, "headshotKills": 0, "heals": 0, "killPoints": 0, "kills": 0, "longestKill": 0, "longestTimeSurvived": 0, "losses": 0, "maxKillStreaks": 0, "mostSurvivalTime": 0, "rankPoints": 0, "rankPointsTitle": "", "revives": 0, "rideDistance": 0, "roadKills": 0, "roundMostKills": 0, "roundsPlayed": 0, "suicides": 0, "swimDistance": 0, "teamKills": 0, "timeSurvived": 0, "top10s": 0, "vehicleDestroys": 0, "walkDistance": 0, "weaponsAcquired": 0, "weeklyKills": 0, "weeklyWins": 0, "winPoints": 0, "wins": 0}, "squad": {"assists": 6, "bestRankPoint": 1079.3654, "boosts": 19, "dBNOs": 29, "dailyKills": 34, "dailyWins": 2, "damageDealt": 3986.9417, "days": 2, "headshotKills": 5, "heals": 13, "killPoints": 0, "kills": 35, "longestKill": 147.75208, "longestTimeSurvived": 1456.714, "losses": 4, "maxKillStreaks": 3, "mostSurvivalTime": 1456.714, "rankPoints": 1079.3654, "rankPointsTitle": "2-5", "revives": 4, "rideDistance": 6303.1973, "roadKills": 0, "roundMostKills": 13, "roundsPlayed": 6, "suicides": 0, "swimDistance": 0, "teamKills": 0, "timeSurvived": 6410.3, "top10s": 4, "vehicleDestroys": 0, "walkDistance": 13895.029, "weaponsAcquired": 32, "weeklyKills": 35, "weeklyWins": 2, "winPoints": 0, "wins": 2}, "squad-fpp": {"assists": 0, "bestRankPoint": 0, "boosts": 0, "dBNOs": 0, "dailyKills": 0, "dailyWins": 0, "damageDealt": 0, "days": 0, "headshotKills": 0, "heals": 0, "killPoints": 0, "kills": 0, "longestKill": 0, "longestTimeSurvived": 0, "losses": 0, "maxKillStreaks": 0, "mostSurvivalTime": 0, "rankPoints": 0, "rankPointsTitle": "", "revives": 0, "rideDistance": 0, "roadKills": 0, "roundMostKills": 0, "roundsPlayed": 0, "suicides": 0, "swimDistance": 0, "teamKills": 0, "timeSurvived": 0, "top10s": 0, "vehicleDestroys": 0, "walkDistance": 0, "weaponsAcquired": 0, "weeklyKills": 0, "weeklyWins": 0, "winPoints": 0, "wins": 0}}}, "relationships": {"matchesSquadFPP": {"data": []}, "season": {"data": {"type": "season", "id": "division.bro.official.pc-2018-02"}}, "player": {"data": {"type": "player", "id": "account.108b0fa8c8ea4cdda8111e7f5f4426a0"}}, "matchesSolo": {"data": []}, "matchesSoloFPP": {"data": []}, "matchesDuo": {"data": [{"type": "match", "id": "3dbb2a7b-42cf-455b-ab99-d32080e1fabd"}, {"type": "match", "id": "c386dedd-1ca2-4cf5-a999-56f7ae84201b"}, {"type": "match", "id": "50ef5692-f4c3-4145-bbea-71f934c3295a"}, {"type": "match", "id": "3992cb17-af0b-4030-a0ea-9884473f6670"}, {"type": "match", "id": "e7e79570-fbd2-4f1b-8f5f-76c404b84147"}, {"type": "match", "id": "f50de1a1-c7a3-41d7-89aa-b412f1a3473f"}, {"type": "match", "id": "793b3204-45b1-4477-b5ad-75cb0bf5e351"}, {"type": "match", "id": "35c6444e-7016-4537-a31a-0ecf862c0389"}, {"type": "match", "id": "56deab8b-990b-4fc6-8228-4d0ff5eb121c"}]}, "matchesDuoFPP": {"data": []}, "matchesSquad": {"data": [{"type": "match", "id": "253c222b-7bd6-4f57-85e3-01eb6639d963"}, {"type": "match", "id": "7a8acc95-849f-45e9-9df0-71bbfa340874"}, {"type": "match", "id": "644d5ce5-7f3c-459d-bfef-47ba2c74a8ff"}, {"type": "match", "id": "cb67497c-d138-4905-a5e9-0d676739ddb2"}, {"type": "match", "id": "ab40e9a2-00a0-40fd-98fd-c70d31356053"}, {"type": "match", "id": "6d9b7625-1f5e-41aa-a80f-9242d80c70e1"}]}}}, "links": {"self": "https://api.pubg.com/shards/kakao/players/account.108b0fa8c8ea4cdda8111e7f5f4426a0/seasons/division.bro.official.pc-2018-02"}, "meta": {}}, "previousSeason": {"data": {"type": "playerSeason", "attributes": {"gameModeStats": {"duo": {"assists": 0, "bestRankPoint": 45.698147, "boosts": 1, "dBNOs": 0, "dailyKills": 0, "dailyWins": 0, "damageDealt": 0, "days": 1, "headshotKills": 0, "heals": 2, "killPoints": 0, "kills": 0, "longestKill": 0, "longestTimeSurvived": 1481.129, "losses": 9, "maxKillStreaks": 0, "mostSurvivalTime": 1481.129, "rankPoints": 45.698147, "rankPointsTitle": "1-5", "revives": 1, "rideDistance": 4128.3467, "roadKills": 0, "roundMostKills": 0, "roundsPlayed": 9, "suicides": 0, "swimDistance": 0, "teamKills": 0, "timeSurvived": 3307.6948, "top10s": 1, "vehicleDestroys": 0, "walkDistance": 3749.1277, "weaponsAcquired": 36, "weeklyKills": 0, "weeklyWins": 0, "winPoints": 0, "wins": 0}, "duo-fpp": {"assists": 0, "bestRankPoint": 0, "boosts": 0, "dBNOs": 0, "dailyKills": 0, "dailyWins": 0, "damageDealt": 0, "days": 0, "headshotKills": 0, "heals": 0, "killPoints": 0, "kills": 0, "longestKill": 0, "longestTimeSurvived": 0, "losses": 0, "maxKillStreaks": 0, "mostSurvivalTime": 0, "rankPoints": 0, "rankPointsTitle": "", "revives": 0, "rideDistance": 0, "roadKills": 0, "roundMostKills": 0, "roundsPlayed": 0, "suicides": 0, "swimDistance": 0, "teamKills": 0, "timeSurvived": 0, "top10s": 0, "vehicleDestroys": 0, "walkDistance": 0, "weaponsAcquired": 0, "weeklyKills": 0, "weeklyWins": 0, "winPoints": 0, "wins": 0}, "solo": {"assists": 0, "bestRankPoint": 0, "boosts": 0, "dBNOs": 0, "dailyKills": 0, "dailyWins": 0, "damageDealt": 0, "days": 0, "headshotKills": 0, "heals": 0, "killPoints": 0, "kills": 0, "longestKill": 0, "longestTimeSurvived": 0, "losses": 0, "maxKillStreaks": 0, "mostSurvivalTime": 0, "rankPoints": 0, "rankPointsTitle": "", "revives": 0, "rideDistance": 0, "roadKills": 0, "roundMostKills": 0, "roundsPlayed": 0, "suicides": 0, "swimDistance": 0, "teamKills": 0, "timeSurvived": 0, "top10s": 0, "vehicleDestroys": 0, "walkDistance": 0, "weaponsAcquired": 0, "weeklyKills": 0, "weeklyWins": 0, "winPoints": 0, "wins": 0}, "solo-fpp": {"assists": 0, "bestRankPoint": 0, "boosts": 0, "dBNOs": 0, "dailyKills": 0, "dailyWins": 0, "damageDealt": 0, "days": 0, "headshotKills": 0, "heals": 0, "killPoints": 0, "kills": 0, "longestKill": 0, "longestTimeSurvived": 0, "losses": 0, "maxKillStreaks": 0, "mostSurvivalTime": 0, "rankPoints": 0, "rankPointsTitle": "", "revives": 0, "rideDistance": 0, "roadKills": 0, "roundMostKills": 0, "roundsPlayed": 0, "suicides": 0, "swimDistance": 0, "teamKills": 0, "timeSurvived": 0, "top10s": 0, "vehicleDestroys": 0, "walkDistance": 0, "weaponsAcquired": 0, "weeklyKills": 0, "weeklyWins": 0, "winPoints": 0, "wins": 0}, "squad": {"assists": 6, "bestRankPoint": 1079.3654, "boosts": 19, "dBNOs": 29, "dailyKills": 34, "dailyWins": 2, "damageDealt": 3986.9417, "days": 2, "headshotKills": 5, "heals": 13, "killPoints": 0, "kills": 35, "longestKill": 147.75208, "longestTimeSurvived": 1456.714, "losses": 4, "maxKillStreaks": 3, "mostSurvivalTime": 1456.714, "rankPoints": 1079.3654, "rankPointsTitle": "2-5", "revives": 4, "rideDistance": 6303.1973, "roadKills": 0, "roundMostKills": 13, "roundsPlayed": 6, "suicides": 0, "swimDistance": 0, "teamKills": 0, "timeSurvived": 6410.3, "top10s": 4, "vehicleDestroys": 0, "walkDistance": 13895.029, "weaponsAcquired": 32, "weeklyKills": 35, "weeklyWins": 2, "winPoints": 0, "wins": 2}, "squad-fpp": {"assists": 0, "bestRankPoint": 0, "boosts": 0, "dBNOs": 0, "dailyKills": 0, "dailyWins": 0, "damageDealt": 0, "days": 0, "headshotKills": 0, "heals": 0, "killPoints": 0, "kills": 0, "longestKill": 0, "longestTimeSurvived": 0, "losses": 0, "maxKillStreaks": 0, "mostSurvivalTime": 0, "rankPoints": 0, "rankPointsTitle": "", "revives": 0, "rideDistance": 0, "roadKills": 0, "roundMostKills": 0, "roundsPlayed": 0, "suicides": 0, "swimDistance": 0, "teamKills": 0, "timeSurvived": 0, "top10s": 0, "vehicleDestroys": 0, "walkDistance": 0, "weaponsAcquired": 0, "weeklyKills": 0, "weeklyWins": 0, "winPoints": 0, "wins": 0}}}, "relationships": {"matchesSolo": {"data": []}, "matchesSoloFPP": {"data": []}, "matchesDuo": {"data": [{"type": "match", "id": "3dbb2a7b-42cf-455b-ab99-d32080e1fabd"}, {"type": "match", "id": "c386dedd-1ca2-4cf5-a999-56f7ae84201b"}, {"type": "match", "id": "50ef5692-f4c3-4145-bbea-71f934c3295a"}, {"type": "match", "id": "3992cb17-af0b-4030-a0ea-9884473f6670"}, {"type": "match", "id": "e7e79570-fbd2-4f1b-8f5f-76c404b84147"}, {"type": "match", "id": "f50de1a1-c7a3-41d7-89aa-b412f1a3473f"}, {"type": "match", "id": "793b3204-45b1-4477-b5ad-75cb0bf5e351"}, {"type": "match", "id": "35c6444e-7016-4537-a31a-0ecf862c0389"}, {"type": "match", "id": "56deab8b-990b-4fc6-8228-4d0ff5eb121c"}]}, "matchesDuoFPP": {"data": []}, "matchesSquad": {"data": [{"type": "match", "id": "253c222b-7bd6-4f57-85e3-01eb6639d963"}, {"type": "match", "id": "7a8acc95-849f-45e9-9df0-71bbfa340874"}, {"type": "match", "id": "644d5ce5-7f3c-459d-bfef-47ba2c74a8ff"}, {"type": "match", "id": "cb67497c-d138-4905-a5e9-0d676739ddb2"}, {"type": "match", "id": "ab40e9a2-00a0-40fd-98fd-c70d31356053"}, {"type": "match", "id": "6d9b7625-1f5e-41aa-a80f-9242d80c70e1"}]}, "matchesSquadFPP": {"data": []}, "season": {"data": {"type": "season", "id": "division.bro.official.pc-2018-02"}}, "player": {"data": {"type": "player", "id": "account.108b0fa8c8ea4cdda8111e7f5f4426a0"}}}}, "links": {"self": "https://api.pubg.com/shards/kakao/players/account.108b0fa8c8ea4cdda8111e7f5f4426a0/seasons/division.bro.official.pc-2018-02"}, "meta": {}}}