{"currentSeason": {"data": {"type": "playerSeason", "attributes": {"gameModeStats": {"duo": {"assists": 4, "bestRankPoint": 219.74023, "boosts": 19, "dBNOs": 19, "dailyKills": 28, "dailyWins": 1, "damageDealt": 3391.03, "days": 1, "headshotKills": 10, "heals": 11, "killPoints": 0, "kills": 28, "longestKill": 330.72144, "longestTimeSurvived": 1448.398, "losses": 8, "maxKillStreaks": 2, "mostSurvivalTime": 1448.398, "rankPoints": 219.74023, "rankPointsTitle": "1-4", "revives": 0, "rideDistance": 617.17535, "roadKills": 0, "roundMostKills": 11, "roundsPlayed": 9, "suicides": 1, "swimDistance": 0, "teamKills": 1, "timeSurvived": 5266.771, "top10s": 4, "vehicleDestroys": 0, "walkDistance": 8244.587, "weaponsAcquired": 41, "weeklyKills": 28, "weeklyWins": 1, "winPoints": 0, "wins": 1}, "duo-fpp": {"assists": 0, "bestRankPoint": 0, "boosts": 0, "dBNOs": 0, "dailyKills": 0, "dailyWins": 0, "damageDealt": 0, "days": 0, "headshotKills": 0, "heals": 0, "killPoints": 0, "kills": 0, "longestKill": 0, "longestTimeSurvived": 0, "losses": 0, "maxKillStreaks": 0, "mostSurvivalTime": 0, "rankPoints": 0, "rankPointsTitle": "", "revives": 0, "rideDistance": 0, "roadKills": 0, "roundMostKills": 0, "roundsPlayed": 0, "suicides": 0, "swimDistance": 0, "teamKills": 0, "timeSurvived": 0, "top10s": 0, "vehicleDestroys": 0, "walkDistance": 0, "weaponsAcquired": 0, "weeklyKills": 0, "weeklyWins": 0, "winPoints": 0, "wins": 0}, "solo": {"assists": 0, "bestRankPoint": 0, "boosts": 0, "dBNOs": 0, "dailyKills": 0, "dailyWins": 0, "damageDealt": 0, "days": 0, "headshotKills": 0, "heals": 0, "killPoints": 0, "kills": 0, "longestKill": 0, "longestTimeSurvived": 0, "losses": 0, "maxKillStreaks": 0, "mostSurvivalTime": 0, "rankPoints": 0, "rankPointsTitle": "", "revives": 0, "rideDistance": 0, "roadKills": 0, "roundMostKills": 0, "roundsPlayed": 0, "suicides": 0, "swimDistance": 0, "teamKills": 0, "timeSurvived": 0, "top10s": 0, "vehicleDestroys": 0, "walkDistance": 0, "weaponsAcquired": 0, "weeklyKills": 0, "weeklyWins": 0, "winPoints": 0, "wins": 0}, "solo-fpp": {"assists": 0, "bestRankPoint": 0, "boosts": 0, "dBNOs": 0, "dailyKills": 0, "dailyWins": 0, "damageDealt": 0, "days": 0, "headshotKills": 0, "heals": 0, "killPoints": 0, "kills": 0, "longestKill": 0, "longestTimeSurvived": 0, "losses": 0, "maxKillStreaks": 0, "mostSurvivalTime": 0, "rankPoints": 0, "rankPointsTitle": "", "revives": 0, "rideDistance": 0, "roadKills": 0, "roundMostKills": 0, "roundsPlayed": 0, "suicides": 0, "swimDistance": 0, "teamKills": 0, "timeSurvived": 0, "top10s": 0, "vehicleDestroys": 0, "walkDistance": 0, "weaponsAcquired": 0, "weeklyKills": 0, "weeklyWins": 0, "winPoints": 0, "wins": 0}, "squad": {"assists": 1, "bestRankPoint": 1014.55994, "boosts": 3, "dBNOs": 3, "dailyKills": 0, "dailyWins": 0, "damageDealt": 501.83804, "days": 2, "headshotKills": 1, "heals": 5, "killPoints": 0, "kills": 1, "longestKill": 21.833323, "longestTimeSurvived": 1450.322, "losses": 5, "maxKillStreaks": 1, "mostSurvivalTime": 1450.322, "rankPoints": 1014.55994, "rankPointsTitle": "2-5", "revives": 0, "rideDistance": 440.20114, "roadKills": 0, "roundMostKills": 1, "roundsPlayed": 5, "suicides": 0, "swimDistance": 0, "teamKills": 0, "timeSurvived": 3151.635, "top10s": 2, "vehicleDestroys": 0, "walkDistance": 3355.6953, "weaponsAcquired": 22, "weeklyKills": 0, "weeklyWins": 0, "winPoints": 0, "wins": 0}, "squad-fpp": {"assists": 0, "bestRankPoint": 0, "boosts": 0, "dBNOs": 0, "dailyKills": 0, "dailyWins": 0, "damageDealt": 0, "days": 0, "headshotKills": 0, "heals": 0, "killPoints": 0, "kills": 0, "longestKill": 0, "longestTimeSurvived": 0, "losses": 0, "maxKillStreaks": 0, "mostSurvivalTime": 0, "rankPoints": 0, "rankPointsTitle": "", "revives": 0, "rideDistance": 0, "roadKills": 0, "roundMostKills": 0, "roundsPlayed": 0, "suicides": 0, "swimDistance": 0, "teamKills": 0, "timeSurvived": 0, "top10s": 0, "vehicleDestroys": 0, "walkDistance": 0, "weaponsAcquired": 0, "weeklyKills": 0, "weeklyWins": 0, "winPoints": 0, "wins": 0}}}, "relationships": {"matchesSquadFPP": {"data": []}, "season": {"data": {"type": "season", "id": "division.bro.official.pc-2018-02"}}, "player": {"data": {"type": "player", "id": "account.67298f9fee8d4dc289ffe8b32c8ea03c"}}, "matchesSolo": {"data": []}, "matchesSoloFPP": {"data": []}, "matchesDuo": {"data": [{"type": "match", "id": "2531715a-c294-44e9-807c-1d17f6aa39d6"}, {"type": "match", "id": "84703aaf-3584-4634-bcdc-6d46b6a88b9c"}, {"type": "match", "id": "462192b0-c77b-4963-8d0a-971ed7922045"}, {"type": "match", "id": "4d07e5aa-7184-4b2a-ba81-1f9b856725a6"}, {"type": "match", "id": "8ce146f9-0969-4522-81c4-db0685b5236b"}, {"type": "match", "id": "a64de06c-62c0-4030-b601-9bf0c577ed3c"}, {"type": "match", "id": "f146c240-ca84-4bbb-b2b2-1f82fa932dc9"}, {"type": "match", "id": "349a2916-023e-453b-b155-5c806255669c"}, {"type": "match", "id": "e6f74701-661e-401e-b22b-92b5e4eef403"}]}, "matchesDuoFPP": {"data": []}, "matchesSquad": {"data": [{"type": "match", "id": "2a49f007-879e-4c83-9b73-f9c66fd50e5b"}, {"type": "match", "id": "b531fc6f-af7a-4c1e-b6bb-a06435db7f7d"}]}}}, "links": {"self": "https://api.pubg.com/shards/kakao/players/account.67298f9fee8d4dc289ffe8b32c8ea03c/seasons/division.bro.official.pc-2018-02"}, "meta": {}}, "previousSeason": {"data": {"type": "playerSeason", "attributes": {"gameModeStats": {"duo": {"assists": 4, "bestRankPoint": 219.74023, "boosts": 19, "dBNOs": 19, "dailyKills": 28, "dailyWins": 1, "damageDealt": 3391.03, "days": 1, "headshotKills": 10, "heals": 11, "killPoints": 0, "kills": 28, "longestKill": 330.72144, "longestTimeSurvived": 1448.398, "losses": 8, "maxKillStreaks": 2, "mostSurvivalTime": 1448.398, "rankPoints": 219.74023, "rankPointsTitle": "1-4", "revives": 0, "rideDistance": 617.17535, "roadKills": 0, "roundMostKills": 11, "roundsPlayed": 9, "suicides": 1, "swimDistance": 0, "teamKills": 1, "timeSurvived": 5266.771, "top10s": 4, "vehicleDestroys": 0, "walkDistance": 8244.587, "weaponsAcquired": 41, "weeklyKills": 28, "weeklyWins": 1, "winPoints": 0, "wins": 1}, "duo-fpp": {"assists": 0, "bestRankPoint": 0, "boosts": 0, "dBNOs": 0, "dailyKills": 0, "dailyWins": 0, "damageDealt": 0, "days": 0, "headshotKills": 0, "heals": 0, "killPoints": 0, "kills": 0, "longestKill": 0, "longestTimeSurvived": 0, "losses": 0, "maxKillStreaks": 0, "mostSurvivalTime": 0, "rankPoints": 0, "rankPointsTitle": "", "revives": 0, "rideDistance": 0, "roadKills": 0, "roundMostKills": 0, "roundsPlayed": 0, "suicides": 0, "swimDistance": 0, "teamKills": 0, "timeSurvived": 0, "top10s": 0, "vehicleDestroys": 0, "walkDistance": 0, "weaponsAcquired": 0, "weeklyKills": 0, "weeklyWins": 0, "winPoints": 0, "wins": 0}, "solo": {"assists": 0, "bestRankPoint": 0, "boosts": 0, "dBNOs": 0, "dailyKills": 0, "dailyWins": 0, "damageDealt": 0, "days": 0, "headshotKills": 0, "heals": 0, "killPoints": 0, "kills": 0, "longestKill": 0, "longestTimeSurvived": 0, "losses": 0, "maxKillStreaks": 0, "mostSurvivalTime": 0, "rankPoints": 0, "rankPointsTitle": "", "revives": 0, "rideDistance": 0, "roadKills": 0, "roundMostKills": 0, "roundsPlayed": 0, "suicides": 0, "swimDistance": 0, "teamKills": 0, "timeSurvived": 0, "top10s": 0, "vehicleDestroys": 0, "walkDistance": 0, "weaponsAcquired": 0, "weeklyKills": 0, "weeklyWins": 0, "winPoints": 0, "wins": 0}, "solo-fpp": {"assists": 0, "bestRankPoint": 0, "boosts": 0, "dBNOs": 0, "dailyKills": 0, "dailyWins": 0, "damageDealt": 0, "days": 0, "headshotKills": 0, "heals": 0, "killPoints": 0, "kills": 0, "longestKill": 0, "longestTimeSurvived": 0, "losses": 0, "maxKillStreaks": 0, "mostSurvivalTime": 0, "rankPoints": 0, "rankPointsTitle": "", "revives": 0, "rideDistance": 0, "roadKills": 0, "roundMostKills": 0, "roundsPlayed": 0, "suicides": 0, "swimDistance": 0, "teamKills": 0, "timeSurvived": 0, "top10s": 0, "vehicleDestroys": 0, "walkDistance": 0, "weaponsAcquired": 0, "weeklyKills": 0, "weeklyWins": 0, "winPoints": 0, "wins": 0}, "squad": {"assists": 1, "bestRankPoint": 1014.55994, "boosts": 3, "dBNOs": 3, "dailyKills": 0, "dailyWins": 0, "damageDealt": 501.83804, "days": 2, "headshotKills": 1, "heals": 5, "killPoints": 0, "kills": 1, "longestKill": 21.833323, "longestTimeSurvived": 1450.322, "losses": 5, "maxKillStreaks": 1, "mostSurvivalTime": 1450.322, "rankPoints": 1014.55994, "rankPointsTitle": "2-5", "revives": 0, "rideDistance": 440.20114, "roadKills": 0, "roundMostKills": 1, "roundsPlayed": 5, "suicides": 0, "swimDistance": 0, "teamKills": 0, "timeSurvived": 3151.635, "top10s": 2, "vehicleDestroys": 0, "walkDistance": 3355.6953, "weaponsAcquired": 22, "weeklyKills": 0, "weeklyWins": 0, "winPoints": 0, "wins": 0}, "squad-fpp": {"assists": 0, "bestRankPoint": 0, "boosts": 0, "dBNOs": 0, "dailyKills": 0, "dailyWins": 0, "damageDealt": 0, "days": 0, "headshotKills": 0, "heals": 0, "killPoints": 0, "kills": 0, "longestKill": 0, "longestTimeSurvived": 0, "losses": 0, "maxKillStreaks": 0, "mostSurvivalTime": 0, "rankPoints": 0, "rankPointsTitle": "", "revives": 0, "rideDistance": 0, "roadKills": 0, "roundMostKills": 0, "roundsPlayed": 0, "suicides": 0, "swimDistance": 0, "teamKills": 0, "timeSurvived": 0, "top10s": 0, "vehicleDestroys": 0, "walkDistance": 0, "weaponsAcquired": 0, "weeklyKills": 0, "weeklyWins": 0, "winPoints": 0, "wins": 0}}}, "relationships": {"matchesSolo": {"data": []}, "matchesSoloFPP": {"data": []}, "matchesDuo": {"data": [{"type": "match", "id": "2531715a-c294-44e9-807c-1d17f6aa39d6"}, {"type": "match", "id": "84703aaf-3584-4634-bcdc-6d46b6a88b9c"}, {"type": "match", "id": "462192b0-c77b-4963-8d0a-971ed7922045"}, {"type": "match", "id": "4d07e5aa-7184-4b2a-ba81-1f9b856725a6"}, {"type": "match", "id": "8ce146f9-0969-4522-81c4-db0685b5236b"}, {"type": "match", "id": "a64de06c-62c0-4030-b601-9bf0c577ed3c"}, {"type": "match", "id": "f146c240-ca84-4bbb-b2b2-1f82fa932dc9"}, {"type": "match", "id": "349a2916-023e-453b-b155-5c806255669c"}, {"type": "match", "id": "e6f74701-661e-401e-b22b-92b5e4eef403"}]}, "matchesDuoFPP": {"data": []}, "matchesSquad": {"data": [{"type": "match", "id": "2a49f007-879e-4c83-9b73-f9c66fd50e5b"}, {"type": "match", "id": "b531fc6f-af7a-4c1e-b6bb-a06435db7f7d"}]}, "matchesSquadFPP": {"data": []}, "season": {"data": {"type": "season", "id": "division.bro.official.pc-2018-02"}}, "player": {"data": {"type": "player", "id": "account.67298f9fee8d4dc289ffe8b32c8ea03c"}}}}, "links": {"self": "https://api.pubg.com/shards/kakao/players/account.67298f9fee8d4dc289ffe8b32c8ea03c/seasons/division.bro.official.pc-2018-02"}, "meta": {}}}