{"currentSeason": {"data": {"type": "playerSeason", "attributes": {"gameModeStats": {"duo": {"assists": 0, "bestRankPoint": 0, "boosts": 0, "dBNOs": 0, "dailyKills": 0, "dailyWins": 0, "damageDealt": 0, "days": 0, "headshotKills": 0, "heals": 0, "killPoints": 0, "kills": 0, "longestKill": 0, "longestTimeSurvived": 0, "losses": 0, "maxKillStreaks": 0, "mostSurvivalTime": 0, "rankPoints": 0, "rankPointsTitle": "", "revives": 0, "rideDistance": 0, "roadKills": 0, "roundMostKills": 0, "roundsPlayed": 0, "suicides": 0, "swimDistance": 0, "teamKills": 0, "timeSurvived": 0, "top10s": 0, "vehicleDestroys": 0, "walkDistance": 0, "weaponsAcquired": 0, "weeklyKills": 0, "weeklyWins": 0, "winPoints": 0, "wins": 0}, "duo-fpp": {"assists": 0, "bestRankPoint": 0, "boosts": 0, "dBNOs": 0, "dailyKills": 0, "dailyWins": 0, "damageDealt": 0, "days": 0, "headshotKills": 0, "heals": 0, "killPoints": 0, "kills": 0, "longestKill": 0, "longestTimeSurvived": 0, "losses": 0, "maxKillStreaks": 0, "mostSurvivalTime": 0, "rankPoints": 0, "rankPointsTitle": "", "revives": 0, "rideDistance": 0, "roadKills": 0, "roundMostKills": 0, "roundsPlayed": 0, "suicides": 0, "swimDistance": 0, "teamKills": 0, "timeSurvived": 0, "top10s": 0, "vehicleDestroys": 0, "walkDistance": 0, "weaponsAcquired": 0, "weeklyKills": 0, "weeklyWins": 0, "winPoints": 0, "wins": 0}, "solo": {"assists": 2, "bestRankPoint": 1203.1719, "boosts": 26, "dBNOs": 0, "dailyKills": 37, "dailyWins": 1, "damageDealt": 4653.459, "days": 1, "headshotKills": 8, "heals": 12, "killPoints": 0, "kills": 37, "longestKill": 295.5873, "longestTimeSurvived": 1453.351, "losses": 9, "maxKillStreaks": 2, "mostSurvivalTime": 1453.351, "rankPoints": 1203.1719, "rankPointsTitle": "2-4", "revives": 0, "rideDistance": 947.84924, "roadKills": 0, "roundMostKills": 10, "roundsPlayed": 10, "suicides": 0, "swimDistance": 0, "teamKills": 0, "timeSurvived": 9058.824, "top10s": 5, "vehicleDestroys": 0, "walkDistance": 18631.793, "weaponsAcquired": 34, "weeklyKills": 37, "weeklyWins": 1, "winPoints": 0, "wins": 1}, "solo-fpp": {"assists": 0, "bestRankPoint": 0, "boosts": 0, "dBNOs": 0, "dailyKills": 0, "dailyWins": 0, "damageDealt": 0, "days": 0, "headshotKills": 0, "heals": 0, "killPoints": 0, "kills": 0, "longestKill": 0, "longestTimeSurvived": 0, "losses": 0, "maxKillStreaks": 0, "mostSurvivalTime": 0, "rankPoints": 0, "rankPointsTitle": "", "revives": 0, "rideDistance": 0, "roadKills": 0, "roundMostKills": 0, "roundsPlayed": 0, "suicides": 0, "swimDistance": 0, "teamKills": 0, "timeSurvived": 0, "top10s": 0, "vehicleDestroys": 0, "walkDistance": 0, "weaponsAcquired": 0, "weeklyKills": 0, "weeklyWins": 0, "winPoints": 0, "wins": 0}, "squad": {"assists": 2, "bestRankPoint": 1026.1038, "boosts": 9, "dBNOs": 11, "dailyKills": 14, "dailyWins": 0, "damageDealt": 1446.7339, "days": 1, "headshotKills": 2, "heals": 9, "killPoints": 0, "kills": 14, "longestKill": 111.21677, "longestTimeSurvived": 1520.897, "losses": 5, "maxKillStreaks": 1, "mostSurvivalTime": 1520.897, "rankPoints": 1026.1038, "rankPointsTitle": "2-5", "revives": 1, "rideDistance": 300.8977, "roadKills": 0, "roundMostKills": 6, "roundsPlayed": 5, "suicides": 1, "swimDistance": 0, "teamKills": 1, "timeSurvived": 3102.083, "top10s": 1, "vehicleDestroys": 0, "walkDistance": 3859.9358, "weaponsAcquired": 18, "weeklyKills": 14, "weeklyWins": 0, "winPoints": 0, "wins": 0}, "squad-fpp": {"assists": 0, "bestRankPoint": 0, "boosts": 0, "dBNOs": 0, "dailyKills": 0, "dailyWins": 0, "damageDealt": 0, "days": 0, "headshotKills": 0, "heals": 0, "killPoints": 0, "kills": 0, "longestKill": 0, "longestTimeSurvived": 0, "losses": 0, "maxKillStreaks": 0, "mostSurvivalTime": 0, "rankPoints": 0, "rankPointsTitle": "", "revives": 0, "rideDistance": 0, "roadKills": 0, "roundMostKills": 0, "roundsPlayed": 0, "suicides": 0, "swimDistance": 0, "teamKills": 0, "timeSurvived": 0, "top10s": 0, "vehicleDestroys": 0, "walkDistance": 0, "weaponsAcquired": 0, "weeklyKills": 0, "weeklyWins": 0, "winPoints": 0, "wins": 0}}}, "relationships": {"matchesSolo": {"data": [{"type": "match", "id": "b83e6b37-6289-4278-94e6-1746343fd8c4"}, {"type": "match", "id": "20b8c5e5-9a5c-4c7a-be7e-0a8652b572f0"}, {"type": "match", "id": "c753a057-f882-4beb-b36a-31f87f96432d"}, {"type": "match", "id": "15bb38b1-10a1-41e7-9bd7-ea763c33ba55"}, {"type": "match", "id": "4800f7ef-a429-4c25-8daa-ed4f4c76f69f"}, {"type": "match", "id": "a286cd20-d108-45d6-bd92-5799ffb0ae36"}, {"type": "match", "id": "8b5103c4-09ee-4cd2-b531-3b515685c2a2"}, {"type": "match", "id": "2eadde80-b778-4c37-b845-37169f63f96c"}, {"type": "match", "id": "14b7e439-8a70-4704-8e70-566958b9832f"}, {"type": "match", "id": "e9ef2a1b-b58a-4321-bb77-d6f0258eed40"}]}, "matchesSoloFPP": {"data": []}, "matchesDuo": {"data": []}, "matchesDuoFPP": {"data": []}, "matchesSquad": {"data": [{"type": "match", "id": "410e373e-6879-4604-89ab-a087a2efc29f"}, {"type": "match", "id": "047f25ce-ac46-48e0-8728-f764c922aa30"}, {"type": "match", "id": "9fb8d8d1-3721-4f41-ba17-078bbe699822"}, {"type": "match", "id": "ff43b494-7a2b-476a-9b49-d9c2821f4c70"}, {"type": "match", "id": "814e623a-6aa8-4f34-be1f-8267e6593f93"}]}, "matchesSquadFPP": {"data": []}, "season": {"data": {"type": "season", "id": "division.bro.official.pc-2018-02"}}, "player": {"data": {"type": "player", "id": "account.757fc127802d48338a040e4d535be3be"}}}}, "links": {"self": "https://api.pubg.com/shards/kakao/players/account.757fc127802d48338a040e4d535be3be/seasons/division.bro.official.pc-2018-02"}, "meta": {}}, "previousSeason": {"data": {"type": "playerSeason", "attributes": {"gameModeStats": {"duo": {"assists": 0, "bestRankPoint": 0, "boosts": 0, "dBNOs": 0, "dailyKills": 0, "dailyWins": 0, "damageDealt": 0, "days": 0, "headshotKills": 0, "heals": 0, "killPoints": 0, "kills": 0, "longestKill": 0, "longestTimeSurvived": 0, "losses": 0, "maxKillStreaks": 0, "mostSurvivalTime": 0, "rankPoints": 0, "rankPointsTitle": "", "revives": 0, "rideDistance": 0, "roadKills": 0, "roundMostKills": 0, "roundsPlayed": 0, "suicides": 0, "swimDistance": 0, "teamKills": 0, "timeSurvived": 0, "top10s": 0, "vehicleDestroys": 0, "walkDistance": 0, "weaponsAcquired": 0, "weeklyKills": 0, "weeklyWins": 0, "winPoints": 0, "wins": 0}, "duo-fpp": {"assists": 0, "bestRankPoint": 0, "boosts": 0, "dBNOs": 0, "dailyKills": 0, "dailyWins": 0, "damageDealt": 0, "days": 0, "headshotKills": 0, "heals": 0, "killPoints": 0, "kills": 0, "longestKill": 0, "longestTimeSurvived": 0, "losses": 0, "maxKillStreaks": 0, "mostSurvivalTime": 0, "rankPoints": 0, "rankPointsTitle": "", "revives": 0, "rideDistance": 0, "roadKills": 0, "roundMostKills": 0, "roundsPlayed": 0, "suicides": 0, "swimDistance": 0, "teamKills": 0, "timeSurvived": 0, "top10s": 0, "vehicleDestroys": 0, "walkDistance": 0, "weaponsAcquired": 0, "weeklyKills": 0, "weeklyWins": 0, "winPoints": 0, "wins": 0}, "solo": {"assists": 2, "bestRankPoint": 1203.1719, "boosts": 26, "dBNOs": 0, "dailyKills": 37, "dailyWins": 1, "damageDealt": 4653.459, "days": 1, "headshotKills": 8, "heals": 12, "killPoints": 0, "kills": 37, "longestKill": 295.5873, "longestTimeSurvived": 1453.351, "losses": 9, "maxKillStreaks": 2, "mostSurvivalTime": 1453.351, "rankPoints": 1203.1719, "rankPointsTitle": "2-4", "revives": 0, "rideDistance": 947.84924, "roadKills": 0, "roundMostKills": 10, "roundsPlayed": 10, "suicides": 0, "swimDistance": 0, "teamKills": 0, "timeSurvived": 9058.824, "top10s": 5, "vehicleDestroys": 0, "walkDistance": 18631.793, "weaponsAcquired": 34, "weeklyKills": 37, "weeklyWins": 1, "winPoints": 0, "wins": 1}, "solo-fpp": {"assists": 0, "bestRankPoint": 0, "boosts": 0, "dBNOs": 0, "dailyKills": 0, "dailyWins": 0, "damageDealt": 0, "days": 0, "headshotKills": 0, "heals": 0, "killPoints": 0, "kills": 0, "longestKill": 0, "longestTimeSurvived": 0, "losses": 0, "maxKillStreaks": 0, "mostSurvivalTime": 0, "rankPoints": 0, "rankPointsTitle": "", "revives": 0, "rideDistance": 0, "roadKills": 0, "roundMostKills": 0, "roundsPlayed": 0, "suicides": 0, "swimDistance": 0, "teamKills": 0, "timeSurvived": 0, "top10s": 0, "vehicleDestroys": 0, "walkDistance": 0, "weaponsAcquired": 0, "weeklyKills": 0, "weeklyWins": 0, "winPoints": 0, "wins": 0}, "squad": {"assists": 2, "bestRankPoint": 1026.1038, "boosts": 9, "dBNOs": 11, "dailyKills": 14, "dailyWins": 0, "damageDealt": 1446.7339, "days": 1, "headshotKills": 2, "heals": 9, "killPoints": 0, "kills": 14, "longestKill": 111.21677, "longestTimeSurvived": 1520.897, "losses": 5, "maxKillStreaks": 1, "mostSurvivalTime": 1520.897, "rankPoints": 1026.1038, "rankPointsTitle": "2-5", "revives": 1, "rideDistance": 300.8977, "roadKills": 0, "roundMostKills": 6, "roundsPlayed": 5, "suicides": 1, "swimDistance": 0, "teamKills": 1, "timeSurvived": 3102.083, "top10s": 1, "vehicleDestroys": 0, "walkDistance": 3859.9358, "weaponsAcquired": 18, "weeklyKills": 14, "weeklyWins": 0, "winPoints": 0, "wins": 0}, "squad-fpp": {"assists": 0, "bestRankPoint": 0, "boosts": 0, "dBNOs": 0, "dailyKills": 0, "dailyWins": 0, "damageDealt": 0, "days": 0, "headshotKills": 0, "heals": 0, "killPoints": 0, "kills": 0, "longestKill": 0, "longestTimeSurvived": 0, "losses": 0, "maxKillStreaks": 0, "mostSurvivalTime": 0, "rankPoints": 0, "rankPointsTitle": "", "revives": 0, "rideDistance": 0, "roadKills": 0, "roundMostKills": 0, "roundsPlayed": 0, "suicides": 0, "swimDistance": 0, "teamKills": 0, "timeSurvived": 0, "top10s": 0, "vehicleDestroys": 0, "walkDistance": 0, "weaponsAcquired": 0, "weeklyKills": 0, "weeklyWins": 0, "winPoints": 0, "wins": 0}}}, "relationships": {"matchesDuo": {"data": []}, "matchesDuoFPP": {"data": []}, "matchesSquad": {"data": [{"type": "match", "id": "410e373e-6879-4604-89ab-a087a2efc29f"}, {"type": "match", "id": "047f25ce-ac46-48e0-8728-f764c922aa30"}, {"type": "match", "id": "9fb8d8d1-3721-4f41-ba17-078bbe699822"}, {"type": "match", "id": "ff43b494-7a2b-476a-9b49-d9c2821f4c70"}, {"type": "match", "id": "814e623a-6aa8-4f34-be1f-8267e6593f93"}]}, "matchesSquadFPP": {"data": []}, "season": {"data": {"type": "season", "id": "division.bro.official.pc-2018-02"}}, "player": {"data": {"type": "player", "id": "account.757fc127802d48338a040e4d535be3be"}}, "matchesSolo": {"data": [{"type": "match", "id": "b83e6b37-6289-4278-94e6-1746343fd8c4"}, {"type": "match", "id": "20b8c5e5-9a5c-4c7a-be7e-0a8652b572f0"}, {"type": "match", "id": "c753a057-f882-4beb-b36a-31f87f96432d"}, {"type": "match", "id": "15bb38b1-10a1-41e7-9bd7-ea763c33ba55"}, {"type": "match", "id": "4800f7ef-a429-4c25-8daa-ed4f4c76f69f"}, {"type": "match", "id": "a286cd20-d108-45d6-bd92-5799ffb0ae36"}, {"type": "match", "id": "8b5103c4-09ee-4cd2-b531-3b515685c2a2"}, {"type": "match", "id": "2eadde80-b778-4c37-b845-37169f63f96c"}, {"type": "match", "id": "14b7e439-8a70-4704-8e70-566958b9832f"}, {"type": "match", "id": "e9ef2a1b-b58a-4321-bb77-d6f0258eed40"}]}, "matchesSoloFPP": {"data": []}}}, "links": {"self": "https://api.pubg.com/shards/kakao/players/account.757fc127802d48338a040e4d535be3be/seasons/division.bro.official.pc-2018-02"}, "meta": {}}}